{
  "name": "preview_wait_for",
  "description": "Wait in the tab selected by tabId, or this agent session's current tab when omitted, until all supplied locator, selector, text, and URL conditions match.",
  "inputSchema": {
    "type": "object",
    "properties": {
      "tabId": {
        "anyOf": [
          {
            "type": "string"
          },
          {
            "type": "null"
          }
        ],
        "description": "Exact collaborative browser tab to target. Omit to use this agent session's current tab."
      },
      "selector": {
        "anyOf": [
          {
            "type": "string"
          },
          {
            "type": "null"
          }
        ],
        "description": "Legacy CSS selector that must match an element. Prefer locator."
      },
      "locator": {
        "anyOf": [
          {
            "type": "string"
          },
          {
            "type": "null"
          }
        ],
        "description": "Playwright selector that must match an element, for example role=button[name='Send']."
      },
      "text": {
        "anyOf": [
          {
            "type": "string"
          },
          {
            "type": "null"
          }
        ],
        "description": "Case-sensitive substring that must appear in visible document text."
      },
      "urlIncludes": {
        "anyOf": [
          {
            "type": "string"
          },
          {
            "type": "null"
          }
        ],
        "description": "Substring that must appear in the current absolute URL."
      },
      "timeoutMs": {
        "anyOf": [
          {
            "type": "integer",
            "allOf": [
              {
                "exclusiveMinimum": 0
              },
              {
                "maximum": 60000,
                "description": "Maximum wait in milliseconds. Defaults to 15000; maximum 60000."
              }
            ]
          },
          {
            "type": "null"
          }
        ],
        "description": "Maximum wait in milliseconds. Defaults to 15000; maximum 60000."
      }
    },
    "additionalProperties": false
  }
}